teklia_toolbox/__init__.py
teklia_toolbox/config.py
teklia_toolbox/pagexml.py
teklia_toolbox/requests.py
teklia_toolbox/time.py
teklia_toolbox/uploads.py
teklia_toolbox/xml.py
tests/conftest.py
tests/test_config.py
tests/test_pagexml.py
tests/test_time.py
tests/test_upload.py
teklia_toolbox-0.1.13.dist-info/METADATA
teklia_toolbox-0.1.13.dist-info/WHEEL
teklia_toolbox-0.1.13.dist-info/top_level.txt
teklia_toolbox-0.1.13.dist-info/RECORD
