Metadata-Version: 2.4
Name: teklia-toolbox
Version: 0.1.13
Author-email: Teklia <contact@teklia.com>
Maintainer-email: Teklia <contact@teklia.com>
Project-URL: Repository, https://gitlab.teklia.com/tools/python-toolbox
Project-URL: Bug Tracker, https://gitlab.teklia.com/tools/python-toolbox/issues
Project-URL: Authors, https://teklia.com
Keywords: python
Classifier: Development Status :: 5 - Production/Stable
Classifier: License :: OSI Approved :: MIT License
Classifier: Programming Language :: Python :: 3 :: Only
Classifier: Programming Language :: Python :: 3.10
Classifier: Programming Language :: Python :: 3.11
Requires-Python: >=3.10
Requires-Dist: arkindex-client==1.1.5
Requires-Dist: lxml==5.2.1
Requires-Dist: PyYAML>=5.4.1
